README.md
setup.py
abnamro/__init__.py
abnamro/challenge.py
abnamro/constants.py
abnamro/schema.py
abnamro/services.py
abnamro/settings.py
abnamro/streams.py
abnamro.egg-info/PKG-INFO
abnamro.egg-info/SOURCES.txt
abnamro.egg-info/dependency_links.txt
abnamro.egg-info/requires.txt
abnamro.egg-info/top_level.txt
abnamro/managers/__init__.py
abnamro/managers/accounts.py
abnamro/managers/authorization.py
abnamro/managers/debitcards.py
abnamro/managers/mutations.py