Metadata-Version: 2.1
Name: abnamro
Version: 2.0.1
Summary: Unofficial ABN AMRO client
Home-page: https://github.com/kinnay/ABN-Amro
Author: Yannik Marchand
Author-email: ymarchand@me.com
License: UNKNOWN
Platform: UNKNOWN
